{"cameraMode":{"drawMode":0,"name":"Shaded","section":"Shading Mode"},"sceneLighting":true,"audioPlay":false,"sceneViewState":{"m_AlwaysRefresh":false,"showFog":true,"showSkybox":true,"showFlares":true,"showImageEffects":true,"showParticleSystems":true,"showVisualEffectGraphs":true,"m_FxEnabled":true},"in2DMode":false,"pivot":{"x":0.0,"y":0.5,"z":0.0},"rotation":{"x":0.0021617210004478695,"y":0.694674551486969,"z":0.001633659703657031,"w":-0.7192178964614868},"size":3.2569570541381838,"orthographic":false}